{"P1": {"labels": ["\u670d\u52a1\u5668"], "postTitle": "Let's Encrypt \u4f7f\u7528\u6559\u7a0b\uff0c\u914d\u5408Nginx\u5f00\u542fHttps", "postUrl": "post/Let%27s%20Encrypt%20-shi-yong-jiao-cheng-%EF%BC%8C-pei-he-Nginx-kai-qi-Https.html", "createdDate": "2024-10-17", "dateLabelColor": "#bc4c00"}, "labelColorDict": {"bug": "#d73a4a", "documentation": "#0075ca", "duplicate": "#cfd3d7", "enhancement": "#a2eeef", "good first issue": "#7057ff", "help wanted": "#008672", "invalid": "#e4e669", "question": "#d876e3", "wontfix": "#ffffff", "\u670d\u52a1\u5668": "#64E5A2"}}